wdq_mcp/__init__.py
wdq_mcp/__main__.py
wdq_mcp/server.py
wdq_mcp-0.1.0.dist-info/METADATA
wdq_mcp-0.1.0.dist-info/WHEEL
wdq_mcp-0.1.0.dist-info/entry_points.txt
wdq_mcp-0.1.0.dist-info/RECORD
