Metadata-Version: 2.4
Name: wdq-mcp
Version: 0.1.0
Summary: 五洞桥社区'小五微网共治共享'微网实格管理智慧平台 MCP 服务包
Project-URL: Homepage, https://github.com/wifiming/wdq-mcp
Project-URL: Repository, https://github.com/wifiming/wdq-mcp.git
Project-URL: Issues, https://github.com/wifiming/wdq-mcp/issues
Project-URL: Documentation, https://github.com/wifiming/wdq-mcp#readme
Author-email: wifiming <sir@wifiming.com>
Maintainer-email: wifiming <sir@wifiming.com>
Keywords: wdq,wudongqiao,五洞桥
Classifier: Development Status :: 4 - Beta
Classifier: Intended Audience :: Developers
Classifier: License :: Other/Proprietary License
Classifier: Operating System :: OS Independent
Classifier: Programming Language :: Python :: 3
Classifier: Programming Language :: Python :: 3.8
Classifier: Programming Language :: Python :: 3.9
Classifier: Programming Language :: Python :: 3.10
Classifier: Programming Language :: Python :: 3.11
Classifier: Programming Language :: Python :: 3.12
Classifier: Topic :: Internet :: WWW/HTTP :: Dynamic Content
Classifier: Topic :: Office/Business :: Groupware
Classifier: Topic :: Software Development :: Libraries :: Python Modules
Requires-Python: >=3.8
Requires-Dist: mcp[cli]>=1.13.1
Requires-Dist: requests>=2.31.0
Provides-Extra: dev
Requires-Dist: black>=23.0.0; extra == 'dev'
Requires-Dist: flake8>=6.0.0; extra == 'dev'
Requires-Dist: isort>=5.12.0; extra == 'dev'
Requires-Dist: mypy>=1.0.0; extra == 'dev'
Requires-Dist: pytest-cov>=4.0.0; extra == 'dev'
Requires-Dist: pytest>=7.0.0; extra == 'dev'
